r00secret/__init__.py
r00secret/core.py
r00secret/helpers/__init__.py
r00secret/helpers/constants.py
r00secret-0.1.3.dist-info/METADATA
r00secret-0.1.3.dist-info/WHEEL
r00secret-0.1.3.dist-info/RECORD
