Metadata-Version: 2.4
Name: r00secret
Version: 0.1.3
Requires-Python: >=3.10
Requires-Dist: python-box>=7.3.2
Requires-Dist: r00logger
Requires-Dist: ruamel-yaml
